xanviewer/__init__.py
xanviewer/animation_state_machine.scxml
xanviewer/animation_viewer.py
xanviewer/assets/xanadu_icon.png
xanviewer/form.ui
xanviewer/fxdata_parser.py
xanviewer/main.py
xanviewer/scene_model.py
xanviewer-0.1.1.dist-info/LICENSE
xanviewer-0.1.1.dist-info/METADATA
xanviewer-0.1.1.dist-info/WHEEL
xanviewer-0.1.1.dist-info/entry_points.txt
xanviewer-0.1.1.dist-info/RECORD
